ephys_anonymizer/__init__.py
ephys_anonymizer/anonymizer.py
ephys_anonymizer/commands/__init__.py
ephys_anonymizer/commands/run.py
ephys_anonymizer-0.1.5.dist-info/LICENSE
ephys_anonymizer-0.1.5.dist-info/METADATA
ephys_anonymizer-0.1.5.dist-info/WHEEL
ephys_anonymizer-0.1.5.dist-info/entry_points.txt
ephys_anonymizer-0.1.5.dist-info/top_level.txt
ephys_anonymizer-0.1.5.dist-info/RECORD
